test_automation_libraries/__init__.py
test_automation_libraries/selenium_lib/__init__.py
test_automation_libraries/selenium_lib/selenium_lib.py
tests/__init__.py
tests/test_selenium_lib/__init__.py
tests/test_selenium_lib/test_selenium_lib.py
test_automation_libraries-0.0.1.dist-info/METADATA
test_automation_libraries-0.0.1.dist-info/WHEEL
test_automation_libraries-0.0.1.dist-info/top_level.txt
test_automation_libraries-0.0.1.dist-info/RECORD
